cli_tupak/__init__.py
cli_tupak/plot_multiple_posteriors.py
tupak/.version
tupak/__init__.py
tupak/conversion.py
tupak/detector.py
tupak/likelihood.py
tupak/prior.py
tupak/result.py
tupak/sampler.py
tupak/source.py
tupak/utils.py
tupak/waveform_generator.py
tupak/core/__init__.py
tupak/core/likelihood.py
tupak/core/prior.py
tupak/core/result.py
tupak/core/sampler.py
tupak/core/utils.py
tupak/gw/__init__.py
tupak/gw/calibration.py
tupak/gw/conversion.py
tupak/gw/detector.py
tupak/gw/likelihood.py
tupak/gw/prior.py
tupak/gw/source.py
tupak/gw/utils.py
tupak/gw/waveform_generator.py
tupak/gw/detectors/CE.interferometer
tupak/gw/detectors/ET.interferometer
tupak/gw/detectors/GEO600.interferometer
tupak/gw/detectors/H1.interferometer
tupak/gw/detectors/K1.interferometer
tupak/gw/detectors/L1.interferometer
tupak/gw/detectors/V1.interferometer
tupak/gw/noise_curves/AdV_asd.txt
tupak/gw/noise_curves/AdV_psd.txt
tupak/gw/noise_curves/CE_asd.txt
tupak/gw/noise_curves/CE_psd.txt
tupak/gw/noise_curves/CE_wb_asd.txt
tupak/gw/noise_curves/CE_wb_psd.txt
tupak/gw/noise_curves/ET_B_asd.txt
tupak/gw/noise_curves/ET_B_psd.txt
tupak/gw/noise_curves/ET_D_asd.txt
tupak/gw/noise_curves/ET_D_psd.txt
tupak/gw/noise_curves/GEO600_S6e_asd.txt
tupak/gw/noise_curves/KAGRA_design_asd.txt
tupak/gw/noise_curves/KAGRA_design_psd.txt
tupak/gw/noise_curves/LIGO_srd_asd.txt
tupak/gw/noise_curves/LIGO_srd_psd.txt
tupak/gw/noise_curves/aLIGO_ZERO_DET_high_P_asd.txt
tupak/gw/noise_curves/aLIGO_ZERO_DET_high_P_psd.txt
tupak/gw/noise_curves/aLIGO_early_asd.txt
tupak/gw/noise_curves/aLIGO_early_high_asd.txt
tupak/gw/noise_curves/aLIGO_early_high_psd.txt
tupak/gw/noise_curves/aLIGO_early_psd.txt
tupak/gw/noise_curves/aLIGO_late_asd.txt
tupak/gw/noise_curves/aLIGO_late_psd.txt
tupak/gw/noise_curves/aLIGO_mid_asd.txt
tupak/gw/noise_curves/aLIGO_mid_psd.txt
tupak/gw/noise_curves/highf_psd.txt
tupak/gw/noise_curves/lisa_asd.txt
tupak-0.2.2.dist-info/METADATA
tupak-0.2.2.dist-info/RECORD
tupak-0.2.2.dist-info/WHEEL
tupak-0.2.2.dist-info/entry_points.txt
tupak-0.2.2.dist-info/top_level.txt
