Metadata-Version: 2.1
Name: tupak
Version: 0.2.2
Summary: The User friendly Parameter estimAtion Kode
Home-page: https://git.ligo.org/Monash/tupak
Author: Greg Ashton, Moritz Huebner, Paul Lasky, Colm Talbot
Author-email: paul.lasky@monash.edu
License: MIT
Platform: UNKNOWN
Requires-Dist: future
Requires-Dist: dynesty
Requires-Dist: corner
Requires-Dist: numpy (>=1.9)
Requires-Dist: matplotlib (>=2.0)
Requires-Dist: deepdish
Requires-Dist: pandas
Requires-Dist: scipy
